{"summaries":[{"symbol":{"__symbol":0},"metadata":{"__symbolic":"class"},"type":{"summaryKind":1,"type":{"reference":{"__symbol":0},"diDeps":[{"isAttribute":false,"isHost":false,"isSelf":false,"isSkipSelf":false,"isOptional":false,"token":{"identifier":{"reference":{"__symbol":1}}}},{"isAttribute":false,"isHost":false,"isSelf":false,"isSkipSelf":false,"isOptional":false,"token":{"identifier":{"reference":{"__symbol":2}}}},{"isAttribute":false,"isHost":false,"isSelf":false,"isSkipSelf":false,"isOptional":false,"token":{"identifier":{"reference":{"__symbol":3}}}},{"isAttribute":false,"isHost":false,"isSelf":false,"isSkipSelf":false,"isOptional":false,"token":{"identifier":{"reference":{"__symbol":4}}}}],"lifecycleHooks":[1,3,6]},"isComponent":true,"selector":"zee-execute-multiple-dialog-tce","inputs":{"releaseId":"releaseId","testcaseIds":"testcaseIds","tceGridRows":"tceGridRows","tcrCatalogTreeName":"tcrCatalogTreeName","tcrCatalogTreeId":"tcrCatalogTreeId","executionIds":"executionIds","statuses":"statuses"},"outputs":{},"hostListeners":{},"hostProperties":{},"hostAttributes":{},"providers":[],"viewProviders":[],"queries":[],"entryComponents":[],"changeDetection":1,"template":{"animations":[],"ngContentSelectors":[],"encapsulation":2}}}],"symbols":[{"__symbol":0,"name":"TceExecuteMultipleComponent","filePath":"/Users/goverdhan.koyalkar/Goverdhan/fayre/app/view/components/tce/operations/tce_execute_multiple.component.d.ts"},{"__symbol":1,"name":"TestcaseExecutionAction","filePath":"/Users/goverdhan.koyalkar/Goverdhan/fayre/app/actions/testcaseExecution.action.d.ts"},{"__symbol":2,"name":"NotificationAction","filePath":"/Users/goverdhan.koyalkar/Goverdhan/fayre/app/actions/notification.action.d.ts"},{"__symbol":3,"name":"NgZone","filePath":"/Users/goverdhan.koyalkar/Goverdhan/fayre/node_modules/@angular/core/src/zone/ng_zone.d.ts"},{"__symbol":4,"name":"ToastrService","filePath":"/Users/goverdhan.koyalkar/Goverdhan/fayre/app/services/toastr.service.d.ts"}]}